scrapifurs/GPTinstructions.py
scrapifurs/__init__.py
scrapifurs/tempCodeRunnerFile.py
scrapifurs/utils.py
scrapifurs/working_example.py
tests/__init__.py
scrapifurs-0.1.2.dist-info/LICENSE
scrapifurs-0.1.2.dist-info/METADATA
scrapifurs-0.1.2.dist-info/WHEEL
scrapifurs-0.1.2.dist-info/top_level.txt
scrapifurs-0.1.2.dist-info/RECORD
